{"nodes": [{"id": "public_pics_reading_sentence_sentence", "label": "Sentence Gap-Fill Illustration (sentence.png)", "file_type": "image", "source_file": "public/pics/reading/sentence.png", "source_location": null, "source_url": null, "captured_at": null, "author": null, "contributor": null}, {"id": "public_pics_reading_sentence_sentence_completion", "label": "Sentence Completion / Gap Fill", "file_type": "concept", "source_file": "public/pics/reading/sentence.png", "source_location": null, "source_url": null, "captured_at": null, "author": null, "contributor": null}, {"id": "public_pics_reading_sentence_missing_word_puzzle", "label": "Missing Word as Puzzle Piece Metaphor", "file_type": "concept", "source_file": "public/pics/reading/sentence.png", "source_location": null, "source_url": null, "captured_at": null, "author": null, "contributor": null}], "edges": [{"source": "public_pics_reading_sentence_sentence", "target": "public_pics_reading_sentence_sentence_completion", "relation": "references", "confidence": "INFERRED", "confidence_score": 0.95, "source_file": "public/pics/reading/sentence.png", "source_location": null, "weight": 1.0}, {"source": "public_pics_reading_sentence_sentence", "target": "public_pics_reading_sentence_missing_word_puzzle", "relation": "references", "confidence": "EXTRACTED", "confidence_score": 1.0, "source_file": "public/pics/reading/sentence.png", "source_location": null, "weight": 1.0}, {"source": "public_pics_reading_sentence_missing_word_puzzle", "target": "public_pics_reading_sentence_sentence_completion", "relation": "rationale_for", "confidence": "INFERRED", "confidence_score": 0.85, "source_file": "public/pics/reading/sentence.png", "source_location": null, "weight": 1.0}], "hyperedges": []}